rans/__init__.py
rans/rANSCoder.py
py_rans-1.0.5.dist-info/LICENSE
py_rans-1.0.5.dist-info/METADATA
py_rans-1.0.5.dist-info/WHEEL
py_rans-1.0.5.dist-info/top_level.txt
py_rans-1.0.5.dist-info/RECORD
