Metadata-Version: 2.1
Name: py-rans
Version: 1.0.5
Summary: A lightweight, pure python implementation of a rANS coder.
Home-page: https://github.com/FGlazov/Python-rANSCoder
Author: Fedor Glazov
Author-email: fedorglazov@gmail.com
License: UNKNOWN
Platform: UNKNOWN
Classifier: Programming Language :: Python :: 3
Classifier: License :: CC0 1.0 Universal (CC0 1.0) Public Domain Dedication
Classifier: Operating System :: OS Independent
Requires-Dist: numba (>=0.56.3)
